cage_api/__init__.py
cage_api/cage.py
cage_api/cage_channel.py
cage_api/cage_err.py
cage_api/cage_page.py
cage_api/cage_par_cl.py
cage_api/thread_write_page.py
cage_api-3.1.0.dist-info/LICENSE
cage_api-3.1.0.dist-info/METADATA
cage_api-3.1.0.dist-info/WHEEL
cage_api-3.1.0.dist-info/top_level.txt
cage_api-3.1.0.dist-info/RECORD
