Metadata-Version: 2.1
Name: cage-api
Version: 3.1.0
Summary: Cage system API
Home-page: https://github.com/Arselon/Cage
Author: Arslan Aliev
Author-email: arslanaliev@yahoo.com
Maintainer: Arslan Aliev
Maintainer-email: arslanaliev@yahoo.com
License: Apache
Keywords: Cage,remote file access
Platform: UNKNOWN
Classifier: Programming Language :: Python :: 3.7
Classifier: Intended Audience :: Developers
Requires-Python: >=3.7
